adeso/__init__.py
adeso/adeso.py
adeso/static/about.html
adeso/static/favicon.png
adeso/static/index.html
adeso/static/robots.txt
adeso/static/steganography.html
adeso/static/_app/version.json
adeso/static/_app/immutable/assets/0.fe90dd52.css
adeso/static/_app/immutable/assets/2.5529f161.css
adeso/static/_app/immutable/assets/4.ef1fb64e.css
adeso/static/_app/immutable/assets/_layout.b3d93ad9.css
adeso/static/_app/immutable/assets/_page.5529f161.css
adeso/static/_app/immutable/assets/_page.ef1fb64e.css
adeso/static/_app/immutable/assets/fira-mono-all-400-normal.1e3b098c.woff
adeso/static/_app/immutable/assets/fira-mono-cyrillic-400-normal.c7d433fd.woff2
adeso/static/_app/immutable/assets/fira-mono-cyrillic-ext-400-normal.3df7909e.woff2
adeso/static/_app/immutable/assets/fira-mono-greek-400-normal.a8be01ce.woff2
adeso/static/_app/immutable/assets/fira-mono-greek-ext-400-normal.9e2fe623.woff2
adeso/static/_app/immutable/assets/fira-mono-latin-400-normal.e43b3538.woff2
adeso/static/_app/immutable/assets/fira-mono-latin-ext-400-normal.6bfabd30.woff2
adeso/static/_app/immutable/assets/github.1ea8d62e.svg
adeso/static/_app/immutable/chunks/environment.9aa685ef.js
adeso/static/_app/immutable/chunks/index.fcfb5454.js
adeso/static/_app/immutable/chunks/scheduler.9254f691.js
adeso/static/_app/immutable/chunks/singletons.5b0b2bfb.js
adeso/static/_app/immutable/chunks/stores.b500bcea.js
adeso/static/_app/immutable/entry/app.788394c9.js
adeso/static/_app/immutable/entry/start.12349697.js
adeso/static/_app/immutable/nodes/0.1a425b9e.js
adeso/static/_app/immutable/nodes/1.5128def2.js
adeso/static/_app/immutable/nodes/2.a3ea31da.js
adeso/static/_app/immutable/nodes/3.d3ecf7d1.js
adeso/static/_app/immutable/nodes/4.fb178ad2.js
adeso-0.0.4.dist-info/METADATA
adeso-0.0.4.dist-info/WHEEL
adeso-0.0.4.dist-info/licenses/LICENSE
adeso-0.0.4.dist-info/RECORD
