Metadata-Version: 2.1
Name: adeso
Version: 0.0.4
Summary: Application for Decryption, Encryption and Steganographic Operations
Project-URL: Github, https://github.com/HartmanAnalytics/adeso
Project-URL: Documentation, https://HartmanAnalytics.github.io/adeso/
Author-email: Eric Jay Hartman <ericjayhartman@gmail.com>
License-File: LICENSE
Classifier: License :: OSI Approved :: GNU Affero General Public License v3
Classifier: Operating System :: OS Independent
Classifier: Programming Language :: Python :: 3
Requires-Python: >=3.11.1
Requires-Dist: bitarray==2.7.6
Requires-Dist: blinker==1.6.2
Requires-Dist: certifi==2023.5.7
Requires-Dist: cffi==1.15.1
Requires-Dist: charset-normalizer==3.1.0
Requires-Dist: click==8.1.3
Requires-Dist: colorama==0.4.6
Requires-Dist: cryptography==41.0.1
Requires-Dist: flask-cors==4.0.0
Requires-Dist: flask==2.3.2
Requires-Dist: ghp-import==2.1.0
Requires-Dist: idna==3.4
Requires-Dist: itsdangerous==2.1.2
Requires-Dist: jinja2==3.1.2
Requires-Dist: markdown==3.3.7
Requires-Dist: markupsafe==2.1.3
Requires-Dist: mergedeep==1.3.4
Requires-Dist: mkdocs-material-extensions==1.1.1
Requires-Dist: mkdocs-material==9.1.18
Requires-Dist: mkdocs==1.4.3
Requires-Dist: numpy==1.25.0
Requires-Dist: packaging==23.1
Requires-Dist: pillow==10.0.0
Requires-Dist: pycparser==2.21
Requires-Dist: pygments==2.15.1
Requires-Dist: pymdown-extensions==10.0.1
Requires-Dist: python-dateutil==2.8.2
Requires-Dist: pyyaml-env-tag==0.1
Requires-Dist: pyyaml==6.0
Requires-Dist: regex==2023.6.3
Requires-Dist: requests==2.31.0
Requires-Dist: six==1.16.0
Requires-Dist: urllib3==2.0.3
Requires-Dist: watchdog==3.0.0
Requires-Dist: werkzeug==2.3.6
